README.rst
setup.cfg
setup.py
bin/solnado
solnado/__init__.py
solnado/client.py
solnado.egg-info/PKG-INFO
solnado.egg-info/SOURCES.txt
solnado.egg-info/dependency_links.txt
solnado.egg-info/requires.txt
solnado.egg-info/top_level.txt
solnado/bin/__init__.py
solnado/bin/cli.py
solnado/bin/collection.py
solnado/bin/core.py
solnado/bin/search.py
solnado/bin/status.py